README.md
setup.py
TwinClient/__init__.py
TwinClient/v20220501/__init__.py
TwinClient/v20220501/base_config.py
TwinClient/v20220501/schema.py
TwinClient/v20220501/twin_api.py
TwinClient/v20220501/twin_asset.py
TwinClient/v20220501/twin_definitions.py
TwinClient/v20220507/__init__.py
TwinClient/v20220507/base_config.py
TwinClient/v20220507/schema.py
TwinClient/v20220507/twin_api.py
TwinClient/v20220507/twin_asset.py
TwinClient/v20220507/twin_definitions.py
twin_client_sdk.egg-info/PKG-INFO
twin_client_sdk.egg-info/SOURCES.txt
twin_client_sdk.egg-info/dependency_links.txt
twin_client_sdk.egg-info/requires.txt
twin_client_sdk.egg-info/top_level.txt