Metadata-Version: 2.1
Name: twin-client-sdk
Version: 0.1.1
Summary: twin client sdk
Home-page: https://github.com/sxhxliang
Author: Shihua Liang
Author-email: sxhx.liang@gmail.com
License: UNKNOWN
Platform: UNKNOWN
Requires-Python: >=3.6
